mle/__init__.py
mle/cli.py
mle/version.py
mle/agents/__init__.py
mle/agents/advisor.py
mle/agents/chat.py
mle/agents/coder.py
mle/agents/debugger.py
mle/agents/planner.py
mle/agents/reporter.py
mle/agents/summarizer.py
mle/function/__init__.py
mle/function/data.py
mle/function/execution.py
mle/function/files.py
mle/function/interaction.py
mle/function/search.py
mle/integration/__init__.py
mle/integration/github.py
mle/integration/google_calendar.py
mle/integration/kaggle.py
mle/integration/local_git.py
mle/model/__init__.py
mle/model/anthropic.py
mle/model/common.py
mle/model/deepseek.py
mle/model/mistral.py
mle/model/ollama.py
mle/model/openai.py
mle/server/__init__.py
mle/server/app.py
mle/utils/__init__.py
mle/utils/cache.py
mle/utils/data.py
mle/utils/memory.py
mle/utils/system.py
mle/workflow/__init__.py
mle/workflow/baseline.py
mle/workflow/chat.py
mle/workflow/kaggle.py
mle/workflow/report.py
tests/__init__.py
mle_agent-0.4.2.dist-info/LICENSE
mle_agent-0.4.2.dist-info/METADATA
mle_agent-0.4.2.dist-info/WHEEL
mle_agent-0.4.2.dist-info/entry_points.txt
mle_agent-0.4.2.dist-info/top_level.txt
mle_agent-0.4.2.dist-info/RECORD
