Metadata-Version: 2.1
Name: mle-agent
Version: 0.4.2
Summary: MLE-agent: An agent to automate your MLE processes
Home-page: https://github.com/MLSysOps/MLE-agent
Download-URL: https://github.com/MLSysOps/MLE-agent/archive/refs/heads/main.zip
Author: Yizheng Huang, Huaizheng Zhang
Author-email: huangyz0918@gmail.com
Keywords: LLM,deep learning,MLOps,shell,neural networks
Classifier: Development Status :: 5 - Production/Stable
Classifier: Intended Audience :: Education
Classifier: Intended Audience :: Financial and Insurance Industry
Classifier: Intended Audience :: Science/Research
Classifier: Intended Audience :: Developers
Classifier: Intended Audience :: Information Technology
Classifier: License :: OSI Approved :: Apache Software License
Classifier: Programming Language :: Python :: 3
Classifier: Operating System :: OS Independent
License-File: LICENSE
Requires-Dist: rich
Requires-Dist: click
Requires-Dist: openai~=1.34.0
Requires-Dist: pyyaml
Requires-Dist: kaggle
Requires-Dist: fastapi
Requires-Dist: uvicorn
Requires-Dist: requests
Requires-Dist: chromadb
Requires-Dist: GitPython
Requires-Dist: onnxruntime
Requires-Dist: questionary
Requires-Dist: pandas~=2.2.2
Requires-Dist: tavily-python
Requires-Dist: instructor
Requires-Dist: langfuse
Requires-Dist: setuptools
Requires-Dist: numexpr~=2.10.1
Requires-Dist: bottleneck~=1.4.0
Requires-Dist: google-api-python-client~=2.143.0
Requires-Dist: google-auth-httplib2~=0.2.0
Requires-Dist: google-auth-oauthlib~=1.2.1
